scadm/__init__.py
scadm/cli.py
scadm/constants.py
scadm/installer.py
scadm/py.typed
scadm/vscode.py
scadm-0.4.5.dist-info/METADATA
scadm-0.4.5.dist-info/WHEEL
scadm-0.4.5.dist-info/entry_points.txt
scadm-0.4.5.dist-info/top_level.txt
scadm-0.4.5.dist-info/RECORD
