Metadata-Version: 2.4
Name: scadm
Version: 0.4.5
Summary: OpenSCAD dependency manager - Install OpenSCAD and manage library dependencies
Author-email: Patrick Pötz <kellervater@gmail.com>
License-Expression: MIT
Project-URL: Homepage, https://github.com/kellerlabs/homeracker
Project-URL: Repository, https://github.com/kellerlabs/homeracker
Project-URL: Documentation, https://github.com/kellerlabs/homeracker/tree/main/cmd/scadm
Project-URL: Issues, https://github.com/kellerlabs/homeracker/issues
Project-URL: Changelog, https://github.com/kellerlabs/homeracker/blob/main/cmd/scadm/CHANGELOG.md
Keywords: openscad,dependency-manager,3d-modeling,scad,libraries
Classifier: Development Status :: 4 - Beta
Classifier: Intended Audience :: Developers
Classifier: Programming Language :: Python :: 3
Classifier: Programming Language :: Python :: 3.11
Classifier: Programming Language :: Python :: 3.12
Classifier: Programming Language :: Python :: 3.13
Classifier: Topic :: Software Development :: Build Tools
Classifier: Topic :: Utilities
Requires-Python: >=3.11
